{
    "KPlugin": {
        "Description": "Belgian national railway.",
        "Description[ca]": "Ferrocarrils nacionals belgues.",
        "Description[nl]": "Belgische nationale spoorweg.",
        "Description[pt]": "Caminhos de ferro nacionais da Bélgica.",
        "Description[sv]": "Belgisk statsjärnväg.",
        "Description[uk]": "Бельгійська державна залізниця.",
        "Description[x-test]": "xxBelgian national railway.xx",
        "Name": "National Railway Company of Belgium (NMBS/SNCB)",
        "Name[ca]": "Companyia Nacional de Ferrocarrils de Bèlgica (NMBS/SNCB)",
        "Name[nl]": "National Railway Company of Belgium (NMBS/SNCB)",
        "Name[pt]": "Companhia Nacional de Caminhos de Ferro da Bélgica (NMBS/SNCB)",
        "Name[sk]": "National Railway Company of Belgium (NMBS/SNCB)",
        "Name[sv]": "Belgiens statsjärnvägsbolag (NMBS/SNCB)",
        "Name[uk]": "Національна залізнична компаній Бельгії (NMBS/SNCB)",
        "Name[x-test]": "xxNational Railway Company of Belgium (NMBS/SNCB)xx"
    },
    "filter": {
        "geo": [
            [
                1.797,
                51.1
            ],
            [
                5.55,
                49.124
            ],
            [
                6.598,
                50.464
            ],
            [
                5.154,
                51.837
            ]
        ]
    },
    "options": {
        "aid": "sncb-mobi",
        "clientId": "SNCB",
        "clientType": "AND",
        "endpoint": "http://www.belgianrail.be/jp/sncb-nmbs-routeplanner/mgate.exe",
        "lineModeMap": {
            "1": "LongDistanceTrain",
            "1024": "Tramway",
            "16": "RapidTransit",
            "256": "Metro",
            "32": "Bus",
            "4": "LongDistanceTrain",
            "512": "Bus",
            "64": "RapidTransit"
        },
        "locationIdentifierType": "sncb",
        "standardLocationIdentifierCountries": [
            88
        ],
        "standardLocationIdentifierType": "uic",
        "version": "1.14"
    },
    "type": "hafas_mgate"
}
