{
    "KPlugin": {
        "Description": "Public transport in Mecklenburg-Western Pomerania, Germany.",
        "Description[ca@valencia]": "Transport públic a Mecklenburg-Pomerània Occidental, Alemanya.",
        "Description[ca]": "Transport públic a Mecklenburg-Pomerània Occidental, Alemanya.",
        "Description[es]": "Transporte público de Mecklemburgo-Pomerania Occidental, Alemania.",
        "Description[et]": "Saksamaa Mecklenburgi-Ees-Pommeri ühistransport.",
        "Description[nl]": "Openbaar vervoer in Mecklenburg-West-Pommeren, Duitsland.",
        "Description[pt]": "Transportes públicos em Mecklenburg-Pomerânia Ocidental, Alemanha.",
        "Description[pt_BR]": "Transporte público em Mecklemburgo-Pomerânia Ocidental, Alemanha.",
        "Description[sv]": "Kollektivtrafik i Mecklenburg-Vorpommern, Tyskland.",
        "Description[uk]": "Дані щодо громадського транспорту у землі Мекленбурґ-Західна Померанія, Німеччина.",
        "Description[x-test]": "xxPublic transport in Mecklenburg-Western Pomerania, Germany.xx",
        "Name": "Verkehrsgesellschaft Mecklenburg-Vorpommern (VMV)",
        "Name[ca@valencia]": "Verkehrsgesellschaft Mecklenburg-Vorpommern (VMV)",
        "Name[ca]": "Verkehrsgesellschaft Mecklenburg-Vorpommern (VMV)",
        "Name[es]": "Verkehrsgesellschaft Mecklenburg-Vorpommern (VMV)",
        "Name[et]": "Verkehrsgesellschaft Mecklenburg-Vorpommern (VMV)",
        "Name[nl]": "Verkehrsgesellschaft Mecklenburg-Vorpommern (VMV)",
        "Name[pt]": "Verkehrsgesellschaft Mecklenburg-Vorpommern (VMV)",
        "Name[pt_BR]": "Verkehrsgesellschaft Mecklenburg-Vorpommern (VMV)",
        "Name[sv]": "Verkehrsgesellschaft Mecklenburg-Vorpommern (VMV)",
        "Name[uk]": "Verkehrsgesellschaft Mecklenburg-Vorpommern (VMV)",
        "Name[x-test]": "xxVerkehrsgesellschaft Mecklenburg-Vorpommern (VMV)xx"
    },
    "filter": {
        "geo": [
            [
                10.7879,
                54.1154
            ],
            [
                10.5114,
                53.0571
            ],
            [
                14.4201,
                53.1954
            ],
            [
                14.0957,
                54.9238
            ]
        ]
    },
    "options": {
        "endpoint": "http://efa.vmv-mbh.de/vmv/"
    },
    "supportedLanguages": [
        "en",
        "de"
    ],
    "timezone": "Europe/Berlin",
    "type": "efa"
}
