{
    "KPlugin": {
        "Description": "Public transport in Lower Saxony, Germany.",
        "Description[ca@valencia]": "Transport públic en la Baixa Saxònia, Alemanya.",
        "Description[ca]": "Transport públic a la Baixa Saxònia, Alemanya.",
        "Description[cs]": "Veřejná doprava v Dolním Sasku, Německo.",
        "Description[de]": "Öffentliche Verkehrsmittel in Niedersachsen, Deutschland.",
        "Description[en_GB]": "Public transport in Lower Saxony, Germany.",
        "Description[es]": "Transporte público de Baja Sajonia, Alemania.",
        "Description[et]": "Saksamaa Alam-Saksimaa ühistransport.",
        "Description[fi]": "Julkinen liikenne Saksan Ala-Saksissa.",
        "Description[fr]": "Transports publics dans la Basse-Saxe, Allemagne.",
        "Description[it]": "Trasporto pubblico in Bassa Sassonia, Germania.",
        "Description[ka]": "საჯარო ტრანსპორტი ქვედა საქსონიაში, გერმანია.",
        "Description[ko]": "독일 니더작센의 대중 교통입니다.",
        "Description[nl]": "Openbaar vervoer in Neder-Saksen, Duitsland.",
        "Description[pl]": "Transport publiczny w Dolnej Saksonii, Niemcy.",
        "Description[pt]": "Transportes públicos da Baixa-Saxónia, Alemanha.",
        "Description[pt_BR]": "Transporte público na Baixa Saxônia, Alemanha.",
        "Description[ru]": "Общественный транспорт в Нижней Саксонии, Германия.",
        "Description[sl]": "Javni prevoz v Spodnji Saški, Nemčija.",
        "Description[sv]": "Kollektivtrafik i Niedersachsen, Tyskland.",
        "Description[tr]": "Almanya, Aşağı Saksonya için yerel taşıma.",
        "Description[uk]": "Дані щодо громадського транспорту у Нижній Саксонії, Німеччина.",
        "Description[x-test]": "xxPublic transport in Lower Saxony, Germany.xx",
        "Description[zh_CN]": "德国下萨克森的公共交通。",
        "Name": "Elektronische Fahrplanauskunft für Niedersachsen und Bremen",
        "Name[ca@valencia]": "Elektronische Fahrplanauskunft für Niedersachsen und Bremen",
        "Name[ca]": "Elektronische Fahrplanauskunft für Niedersachsen und Bremen",
        "Name[cs]": "Elektronische Fahrplanauskunft für Niedersachsen und Bremen",
        "Name[de]": "Elektronische Fahrplanauskunft für Niedersachsen und Bremen",
        "Name[en_GB]": "Elektronische Fahrplanauskunft für Niedersachsen und Bremen",
        "Name[es]": "Elektronische Fahrplanauskunft für Niedersachsen und Bremen",
        "Name[et]": "Alam-Saksimaa ja Bremeni elektrooniline sõiduplaan",
        "Name[fi]": "Elektronische Fahrplanauskunft für Niedersachsen und Bremen",
        "Name[fr]": "Elektronische Fahrplanauskunft für Niedersachsen und Bremen",
        "Name[it]": "Elektronische Fahrplanauskunft für Niedersachsen und Bremen",
        "Name[ka]": "Elektronische Fahrplanauskunft für Niedersachsen und Bremen",
        "Name[ko]": "니더작센 및 브레멘 전자 시간표",
        "Name[nl]": "Elektronische Fahrplanauskunft für Niedersachsen und Bremen",
        "Name[pl]": "Elektroniczne planowanie podróży dla Dolnej Saksonii i Bremen",
        "Name[pt]": "Elektronische Fahrplanauskunft für Niedersachsen und Bremen",
        "Name[pt_BR]": "Elektronische Fahrplanauskunft für Niedersachsen und Bremen",
        "Name[ru]": "Elektronische Fahrplanauskunft für Niedersachsen und Bremen",
        "Name[sl]": "Elektronische Fahrplanauskunft für Niedersachsen und Bremen",
        "Name[sv]": "Elektronische Fahrplanauskunft für Niedersachsen und Bremen",
        "Name[tr]": "Elektronische Fahrplanauskunft für Niedersachsen und Bremen",
        "Name[uk]": "Elektronische Fahrplanauskunft für Niedersachsen und Bremen",
        "Name[x-test]": "xxElektronische Fahrplanauskunft für Niedersachsen und Bremenxx"
    },
    "coverage": {
        "anyCoverage": {
            "area": {
                "coordinates": [
                    [
                        [
                            6.8558,
                            53.8848
                        ],
                        [
                            6.6065,
                            52.0076
                        ],
                        [
                            10.7129,
                            51.0397
                        ],
                        [
                            11.6759,
                            53.1955
                        ],
                        [
                            9.6178,
                            53.9532
                        ],
                        [
                            6.8558,
                            53.8848
                        ]
                    ]
                ],
                "type": "Polygon"
            },
            "region": [
                "DE-NI"
            ]
        }
    },
    "options": {
        "endpoint": "https://efa29.efa.de/efaws2/default/",
        "mId": "efa_29"
    },
    "supportedLanguages": [
        "en",
        "de"
    ],
    "timezone": "Europe/Berlin",
    "type": {
        "efa": true
    }
}
