{
    "KPlugin": {
        "Description": "Public transport in and around Portland, Oregon, US.",
        "Name": "TriMet"
    },
    "coverage": {
        "anyCoverage": {
            "area": {
                "coordinates": [
                    [
                        [
                            -123.799993,
                            45.959999
                        ],
                        [
                            -121.500002,
                            45.959999
                        ],
                        [
                            -121.500002,
                            44.680003
                        ],
                        [
                            -123.799993,
                            44.680003
                        ],
                        [
                            -123.799993,
                            45.959999
                        ]
                    ]
                ],
                "type": "Polygon"
            },
            "region": [
                "US-OR"
            ]
        }
    },
    "options": {
        "endpoint": "https://maps.trimet.org/otp_mod/"
    },
    "type": {
        "otpRest": true
    }
}
