[
    {
        "disruptionEffect": "NormalService",
        "expectedDepartureTime": "2021-09-10T19:41:00Z",
        "expectedPlatform": "1",
        "notes": [
            "<b>Linienaenderung</b><br/>Geänderte Verkehrslenkung B170 und Sperrung Boderitzer Straße Ost in Bannewitz"
        ],
        "route": {
            "direction": "Dresden Pirnaischer Platz",
            "line": {
                "mode": "Bus",
                "name": "360",
                "operatorIdentifiers": {
                    "test_id": "voe:3"
                }
            }
        },
        "scheduledDepartureTime": "2021-09-10T19:41:00Z",
        "scheduledPlatform": "3",
        "stopPoint": {
            "identifier": {
                "ifopt": "de:14612:131:1:1",
                "test_id": "de:14612:131:1:1"
            },
            "name": "Dresden Reichenbachstraße"
        }
    },
    {
        "disruptionEffect": "NormalService",
        "expectedDepartureTime": "2021-09-10T19:41:00Z",
        "route": {
            "direction": "Weixdorf",
            "line": {
                "mode": "Tramway",
                "name": "7",
                "operatorIdentifiers": {
                    "test_id": "voe:16"
                }
            }
        },
        "scheduledDepartureTime": "2021-09-10T19:41:00Z",
        "scheduledPlatform": "1",
        "stopPoint": {
            "identifier": {
                "ifopt": "de:14612:32:1:1",
                "test_id": "de:14612:32:1:1"
            },
            "name": "Dresden Hauptbahnhof Nord"
        }
    }
]
