[
    {
        "disruptionEffect": "NormalService",
        "route": {
            "direction": "Frankfurt (Oder), Bahnhof",
            "line": {
                "mode": "LocalTrain",
                "name": "RE10",
                "operatorName": "DB Regio AG Nordost"
            }
        },
        "scheduledDepartureTime": "2024-02-11T12:12:00Z",
        "stopPoint": {
            "country": "DE",
            "identifier": {
                "motis": "de:14713:8010205_G"
            },
            "latitude": 51.34547424316406,
            "longitude": 12.382063865661621,
            "name": "Leipzig Hbf",
            "region": "DE-SN",
            "type": "Stop"
        }
    },
    {
        "disruptionEffect": "NormalService",
        "route": {
            "direction": "Hoyerswerda Bahnhof",
            "line": {
                "mode": "LocalTrain",
                "name": "RE11",
                "operatorName": "DB Regio AG Nordost"
            }
        },
        "scheduledDepartureTime": "2024-02-11T12:12:00Z",
        "stopPoint": {
            "country": "DE",
            "identifier": {
                "motis": "de:14713:8010205_G"
            },
            "latitude": 51.34547424316406,
            "longitude": 12.382063865661621,
            "name": "Leipzig Hbf",
            "region": "DE-SN",
            "type": "Stop"
        }
    },
    {
        "disruptionEffect": "NormalService",
        "route": {
            "direction": "S+U Berlin Hauptbahnhof",
            "line": {
                "mode": "LongDistanceTrain",
                "name": "ICE 692",
                "operatorName": "DB Fernverkehr AG"
            }
        },
        "scheduledArrivalTime": "2024-02-11T12:10:00Z",
        "scheduledDepartureTime": "2024-02-11T12:16:00Z",
        "stopPoint": {
            "country": "DE",
            "identifier": {
                "motis": "de:14713:8010205_G"
            },
            "latitude": 51.34547424316406,
            "longitude": 12.382063865661621,
            "name": "Leipzig Hbf",
            "region": "DE-SN",
            "type": "Stop"
        }
    },
    {
        "disruptionEffect": "NormalService",
        "route": {
            "direction": "Eisenach",
            "line": {
                "mode": "LocalTrain",
                "name": "RB20",
                "operatorName": "Abellio Rail Mitteldeutschland GmbH"
            }
        },
        "scheduledDepartureTime": "2024-02-11T12:19:00Z",
        "stopPoint": {
            "country": "DE",
            "identifier": {
                "motis": "de:14713:8010205_G"
            },
            "latitude": 51.34547424316406,
            "longitude": 12.382063865661621,
            "name": "Leipzig Hbf",
            "region": "DE-SN",
            "type": "Stop"
        }
    },
    {
        "disruptionEffect": "NormalService",
        "route": {
            "direction": "Chemnitz, Hauptbahnhof",
            "line": {
                "mode": "LocalTrain",
                "name": "RE6",
                "operatorName": "Mitteldeutsche Regiobahn"
            }
        },
        "scheduledDepartureTime": "2024-02-11T12:22:00Z",
        "stopPoint": {
            "country": "DE",
            "identifier": {
                "motis": "de:14713:8010205_G"
            },
            "latitude": 51.34547424316406,
            "longitude": 12.382063865661621,
            "name": "Leipzig Hbf",
            "region": "DE-SN",
            "type": "Stop"
        }
    },
    {
        "disruptionEffect": "NormalService",
        "route": {
            "direction": "Dresden Hauptbahnhof",
            "line": {
                "mode": "LongDistanceTrain",
                "name": "IC 2553",
                "operatorName": "DB Fernverkehr AG"
            }
        },
        "scheduledArrivalTime": "2024-02-11T12:21:00Z",
        "scheduledDepartureTime": "2024-02-11T12:31:00Z",
        "stopPoint": {
            "country": "DE",
            "identifier": {
                "motis": "de:14713:8010205_G"
            },
            "latitude": 51.34547424316406,
            "longitude": 12.382063865661621,
            "name": "Leipzig Hbf",
            "region": "DE-SN",
            "type": "Stop"
        }
    },
    {
        "disruptionEffect": "NormalService",
        "route": {
            "direction": "Frankfurt (Main) Hauptbahnhof",
            "line": {
                "mode": "LongDistanceTrain",
                "name": "ICE 1558",
                "operatorName": "DB Fernverkehr AG"
            }
        },
        "scheduledArrivalTime": "2024-02-11T12:26:00Z",
        "scheduledDepartureTime": "2024-02-11T12:33:00Z",
        "stopPoint": {
            "country": "DE",
            "identifier": {
                "motis": "de:14713:8010205_G"
            },
            "latitude": 51.34547424316406,
            "longitude": 12.382063865661621,
            "name": "Leipzig Hbf",
            "region": "DE-SN",
            "type": "Stop"
        }
    },
    {
        "disruptionEffect": "NormalService",
        "route": {
            "direction": "Geithain",
            "line": {
                "mode": "LocalTrain",
                "name": "RB113",
                "operatorName": "DB Regio AG Südost"
            }
        },
        "scheduledDepartureTime": "2024-02-11T12:34:00Z",
        "stopPoint": {
            "country": "DE",
            "identifier": {
                "motis": "de:14713:8010205_G"
            },
            "latitude": 51.34547424316406,
            "longitude": 12.382063865661621,
            "name": "Leipzig Hbf",
            "region": "DE-SN",
            "type": "Stop"
        }
    },
    {
        "disruptionEffect": "NormalService",
        "route": {
            "direction": "Norddeich(Norden) Mole",
            "line": {
                "mode": "LongDistanceTrain",
                "name": "IC 2036",
                "operatorName": "DB Fernverkehr AG"
            }
        },
        "scheduledDepartureTime": "2024-02-11T12:42:00Z",
        "stopPoint": {
            "country": "DE",
            "identifier": {
                "motis": "de:14713:8010205_G"
            },
            "latitude": 51.34547424316406,
            "longitude": 12.382063865661621,
            "name": "Leipzig Hbf",
            "region": "DE-SN",
            "type": "Stop"
        }
    },
    {
        "disruptionEffect": "NormalService",
        "route": {
            "direction": "München Hbf",
            "line": {
                "mode": "LongDistanceTrain",
                "name": "ICE 509",
                "operatorName": "DB Fernverkehr AG"
            }
        },
        "scheduledArrivalTime": "2024-02-11T12:42:00Z",
        "scheduledDepartureTime": "2024-02-11T12:48:00Z",
        "stopPoint": {
            "country": "DE",
            "identifier": {
                "motis": "de:14713:8010205_G"
            },
            "latitude": 51.34547424316406,
            "longitude": 12.382063865661621,
            "name": "Leipzig Hbf",
            "region": "DE-SN",
            "type": "Stop"
        }
    },
    {
        "disruptionEffect": "NormalService",
        "route": {
            "direction": "Karlsruhe Hauptbahnhof",
            "line": {
                "mode": "LongDistanceTrain",
                "name": "IC 2062",
                "operatorName": "DB Fernverkehr AG"
            }
        },
        "scheduledDepartureTime": "2024-02-11T12:49:00Z",
        "stopPoint": {
            "country": "DE",
            "identifier": {
                "motis": "de:14713:8010205_G"
            },
            "latitude": 51.34547424316406,
            "longitude": 12.382063865661621,
            "name": "Leipzig Hbf",
            "region": "DE-SN",
            "type": "Stop"
        }
    },
    {
        "disruptionEffect": "NormalService",
        "route": {
            "direction": "Saalfeld (Saale)",
            "line": {
                "mode": "LocalTrain",
                "name": "RB22",
                "operatorName": "Erfurter Bahn"
            }
        },
        "scheduledDepartureTime": "2024-02-11T12:54:00Z",
        "stopPoint": {
            "country": "DE",
            "identifier": {
                "motis": "de:14713:8010205_G"
            },
            "latitude": 51.34547424316406,
            "longitude": 12.382063865661621,
            "name": "Leipzig Hbf",
            "region": "DE-SN",
            "type": "Stop"
        }
    },
    {
        "disruptionEffect": "NormalService",
        "route": {
            "direction": "Hof Hbf",
            "line": {
                "mode": "LocalTrain",
                "name": "RB13",
                "operatorName": "Erfurter Bahn"
            }
        },
        "scheduledDepartureTime": "2024-02-11T12:54:00Z",
        "stopPoint": {
            "country": "DE",
            "identifier": {
                "motis": "de:14713:8010205_G"
            },
            "latitude": 51.34547424316406,
            "longitude": 12.382063865661621,
            "name": "Leipzig Hbf",
            "region": "DE-SN",
            "type": "Stop"
        }
    },
    {
        "disruptionEffect": "NormalService",
        "route": {
            "direction": "",
            "line": {
                "mode": "LongDistanceTrain",
                "name": "ICE 1211",
                "operatorName": "DB Fernverkehr AG"
            }
        },
        "scheduledArrivalTime": "2024-02-11T12:47:00Z",
        "scheduledDepartureTime": "2024-02-11T12:58:00Z",
        "stopPoint": {
            "country": "DE",
            "identifier": {
                "motis": "de:14713:8010205_G"
            },
            "latitude": 51.34547424316406,
            "longitude": 12.382063865661621,
            "name": "Leipzig Hbf",
            "region": "DE-SN",
            "type": "Stop"
        }
    },
    {
        "disruptionEffect": "NormalService",
        "route": {
            "direction": "Dresden Hauptbahnhof",
            "line": {
                "mode": "LocalTrain",
                "name": "RE50",
                "operatorName": "DB Regio AG Südost"
            }
        },
        "scheduledDepartureTime": "2024-02-11T13:00:00Z",
        "stopPoint": {
            "country": "DE",
            "identifier": {
                "motis": "de:14713:8010205_G"
            },
            "latitude": 51.34547424316406,
            "longitude": 12.382063865661621,
            "name": "Leipzig Hbf",
            "region": "DE-SN",
            "type": "Stop"
        }
    },
    {
        "disruptionEffect": "NormalService",
        "route": {
            "direction": "Magdeburg Hbf",
            "line": {
                "mode": "LocalTrain",
                "name": "RE13",
                "operatorName": "DB Regio AG Südost"
            }
        },
        "scheduledDepartureTime": "2024-02-11T13:04:00Z",
        "stopPoint": {
            "country": "DE",
            "identifier": {
                "motis": "de:14713:8010205_G"
            },
            "latitude": 51.34547424316406,
            "longitude": 12.382063865661621,
            "name": "Leipzig Hbf",
            "region": "DE-SN",
            "type": "Stop"
        }
    },
    {
        "disruptionEffect": "NormalService",
        "route": {
            "direction": "Döbeln, Hauptbahnhof",
            "line": {
                "mode": "LocalTrain",
                "name": "RB110",
                "operatorName": "Mitteldeutsche Regiobahn"
            }
        },
        "scheduledDepartureTime": "2024-02-11T13:06:00Z",
        "stopPoint": {
            "country": "DE",
            "identifier": {
                "motis": "de:14713:8010205_G"
            },
            "latitude": 51.34547424316406,
            "longitude": 12.382063865661621,
            "name": "Leipzig Hbf",
            "region": "DE-SN",
            "type": "Stop"
        }
    },
    {
        "disruptionEffect": "NormalService",
        "route": {
            "direction": "Hamburg-Altona",
            "line": {
                "mode": "LongDistanceTrain",
                "name": "ICE 508",
                "operatorName": "DB Fernverkehr AG"
            }
        },
        "scheduledArrivalTime": "2024-02-11T13:10:00Z",
        "scheduledDepartureTime": "2024-02-11T13:16:00Z",
        "stopPoint": {
            "country": "DE",
            "identifier": {
                "motis": "de:14713:8010205_G"
            },
            "latitude": 51.34547424316406,
            "longitude": 12.382063865661621,
            "name": "Leipzig Hbf",
            "region": "DE-SN",
            "type": "Stop"
        }
    },
    {
        "disruptionEffect": "NormalService",
        "route": {
            "direction": "Eisenach",
            "line": {
                "mode": "LocalTrain",
                "name": "RB20",
                "operatorName": "Abellio Rail Mitteldeutschland GmbH"
            }
        },
        "scheduledDepartureTime": "2024-02-11T13:19:00Z",
        "stopPoint": {
            "country": "DE",
            "identifier": {
                "motis": "de:14713:8010205_G"
            },
            "latitude": 51.34547424316406,
            "longitude": 12.382063865661621,
            "name": "Leipzig Hbf",
            "region": "DE-SN",
            "type": "Stop"
        }
    },
    {
        "disruptionEffect": "NormalService",
        "route": {
            "direction": "Chemnitz, Hauptbahnhof",
            "line": {
                "mode": "LocalTrain",
                "name": "RE6",
                "operatorName": "Mitteldeutsche Regiobahn"
            }
        },
        "scheduledDepartureTime": "2024-02-11T13:22:00Z",
        "stopPoint": {
            "country": "DE",
            "identifier": {
                "motis": "de:14713:8010205_G"
            },
            "latitude": 51.34547424316406,
            "longitude": 12.382063865661621,
            "name": "Leipzig Hbf",
            "region": "DE-SN",
            "type": "Stop"
        }
    },
    {
        "disruptionEffect": "NormalService",
        "route": {
            "direction": "Leipzig Hbf",
            "line": {
                "mode": "LocalTrain",
                "name": "RE15",
                "operatorName": "Abellio Rail Mitteldeutschland GmbH"
            }
        },
        "scheduledArrivalTime": "2024-02-11T12:08:00Z",
        "stopPoint": {
            "country": "DE",
            "identifier": {
                "motis": "de:14713:8010205_G"
            },
            "latitude": 51.34547424316406,
            "longitude": 12.382063865661621,
            "name": "Leipzig Hbf",
            "region": "DE-SN",
            "type": "Stop"
        }
    },
    {
        "disruptionEffect": "NormalService",
        "route": {
            "direction": "Leipzig Hbf",
            "line": {
                "mode": "LocalTrain",
                "name": "RB113",
                "operatorName": "DB Regio AG Südost"
            }
        },
        "scheduledArrivalTime": "2024-02-11T12:22:00Z",
        "stopPoint": {
            "country": "DE",
            "identifier": {
                "motis": "de:14713:8010205_G"
            },
            "latitude": 51.34547424316406,
            "longitude": 12.382063865661621,
            "name": "Leipzig Hbf",
            "region": "DE-SN",
            "type": "Stop"
        }
    },
    {
        "disruptionEffect": "NormalService",
        "route": {
            "direction": "Leipzig Hbf",
            "line": {
                "mode": "LocalTrain",
                "name": "RE6",
                "operatorName": "Mitteldeutsche Regiobahn"
            }
        },
        "scheduledArrivalTime": "2024-02-11T12:31:00Z",
        "stopPoint": {
            "country": "DE",
            "identifier": {
                "motis": "de:14713:8010205_G"
            },
            "latitude": 51.34547424316406,
            "longitude": 12.382063865661621,
            "name": "Leipzig Hbf",
            "region": "DE-SN",
            "type": "Stop"
        }
    },
    {
        "disruptionEffect": "NormalService",
        "route": {
            "direction": "Leipzig Hbf",
            "line": {
                "mode": "LocalTrain",
                "name": "RB20",
                "operatorName": "Abellio Rail Mitteldeutschland GmbH"
            }
        },
        "scheduledArrivalTime": "2024-02-11T12:39:00Z",
        "stopPoint": {
            "country": "DE",
            "identifier": {
                "motis": "de:14713:8010205_G"
            },
            "latitude": 51.34547424316406,
            "longitude": 12.382063865661621,
            "name": "Leipzig Hbf",
            "region": "DE-SN",
            "type": "Stop"
        }
    },
    {
        "disruptionEffect": "NormalService",
        "route": {
            "direction": "Leipzig Hbf",
            "line": {
                "mode": "LocalTrain",
                "name": "RE50",
                "operatorName": "DB Regio AG Südost"
            }
        },
        "scheduledArrivalTime": "2024-02-11T12:50:00Z",
        "stopPoint": {
            "country": "DE",
            "identifier": {
                "motis": "de:14713:8010205_G"
            },
            "latitude": 51.34547424316406,
            "longitude": 12.382063865661621,
            "name": "Leipzig Hbf",
            "region": "DE-SN",
            "type": "Stop"
        }
    },
    {
        "disruptionEffect": "NormalService",
        "route": {
            "direction": "Leipzig Hbf",
            "line": {
                "mode": "LocalTrain",
                "name": "RE13",
                "operatorName": "DB Regio AG Südost"
            }
        },
        "scheduledArrivalTime": "2024-02-11T12:56:00Z",
        "stopPoint": {
            "country": "DE",
            "identifier": {
                "motis": "de:14713:8010205_G"
            },
            "latitude": 51.34547424316406,
            "longitude": 12.382063865661621,
            "name": "Leipzig Hbf",
            "region": "DE-SN",
            "type": "Stop"
        }
    },
    {
        "disruptionEffect": "NormalService",
        "route": {
            "direction": "Leipzig Hbf",
            "line": {
                "mode": "LocalTrain",
                "name": "RB110",
                "operatorName": "Mitteldeutsche Regiobahn"
            }
        },
        "scheduledArrivalTime": "2024-02-11T13:00:00Z",
        "stopPoint": {
            "country": "DE",
            "identifier": {
                "motis": "de:14713:8010205_G"
            },
            "latitude": 51.34547424316406,
            "longitude": 12.382063865661621,
            "name": "Leipzig Hbf",
            "region": "DE-SN",
            "type": "Stop"
        }
    },
    {
        "disruptionEffect": "NormalService",
        "route": {
            "direction": "Leipzig Hbf",
            "line": {
                "mode": "LongDistanceTrain",
                "name": "IC 2063",
                "operatorName": "DB Fernverkehr AG"
            }
        },
        "scheduledArrivalTime": "2024-02-11T13:04:00Z",
        "stopPoint": {
            "country": "DE",
            "identifier": {
                "motis": "de:14713:8010205_G"
            },
            "latitude": 51.34547424316406,
            "longitude": 12.382063865661621,
            "name": "Leipzig Hbf",
            "region": "DE-SN",
            "type": "Stop"
        }
    },
    {
        "disruptionEffect": "NormalService",
        "route": {
            "direction": "Leipzig Hbf",
            "line": {
                "mode": "LocalTrain",
                "name": "RB22",
                "operatorName": "Erfurter Bahn"
            }
        },
        "scheduledArrivalTime": "2024-02-11T13:08:00Z",
        "stopPoint": {
            "country": "DE",
            "identifier": {
                "motis": "de:14713:8010205_G"
            },
            "latitude": 51.34547424316406,
            "longitude": 12.382063865661621,
            "name": "Leipzig Hbf",
            "region": "DE-SN",
            "type": "Stop"
        }
    },
    {
        "disruptionEffect": "NormalService",
        "route": {
            "direction": "Leipzig Hbf",
            "line": {
                "mode": "LocalTrain",
                "name": "RB13",
                "operatorName": "Erfurter Bahn"
            }
        },
        "scheduledArrivalTime": "2024-02-11T13:08:00Z",
        "stopPoint": {
            "country": "DE",
            "identifier": {
                "motis": "de:14713:8010205_G"
            },
            "latitude": 51.34547424316406,
            "longitude": 12.382063865661621,
            "name": "Leipzig Hbf",
            "region": "DE-SN",
            "type": "Stop"
        }
    },
    {
        "disruptionEffect": "NormalService",
        "route": {
            "direction": "Leipzig Hbf",
            "line": {
                "mode": "LongDistanceTrain",
                "name": "IC 2037",
                "operatorName": "DB Fernverkehr AG"
            }
        },
        "scheduledArrivalTime": "2024-02-11T13:15:00Z",
        "stopPoint": {
            "country": "DE",
            "identifier": {
                "motis": "de:14713:8010205_G"
            },
            "latitude": 51.34547424316406,
            "longitude": 12.382063865661621,
            "name": "Leipzig Hbf",
            "region": "DE-SN",
            "type": "Stop"
        }
    },
    {
        "disruptionEffect": "NormalService",
        "route": {
            "direction": "Magdeburg Hbf",
            "line": {
                "mode": "LongDistanceTrain",
                "name": "IC 2552",
                "operatorName": "DB Fernverkehr AG"
            }
        },
        "scheduledArrivalTime": "2024-02-11T13:20:00Z",
        "stopPoint": {
            "country": "DE",
            "identifier": {
                "motis": "de:14713:8010205_G"
            },
            "latitude": 51.34547424316406,
            "longitude": 12.382063865661621,
            "name": "Leipzig Hbf",
            "region": "DE-SN",
            "type": "Stop"
        }
    },
    {
        "disruptionEffect": "NormalService",
        "route": {
            "direction": "Leipzig Hbf",
            "line": {
                "mode": "LocalTrain",
                "name": "RB113",
                "operatorName": "DB Regio AG Südost"
            }
        },
        "scheduledArrivalTime": "2024-02-11T13:22:00Z",
        "stopPoint": {
            "country": "DE",
            "identifier": {
                "motis": "de:14713:8010205_G"
            },
            "latitude": 51.34547424316406,
            "longitude": 12.382063865661621,
            "name": "Leipzig Hbf",
            "region": "DE-SN",
            "type": "Stop"
        }
    },
    {
        "disruptionEffect": "NormalService",
        "route": {
            "direction": "Dresden Hauptbahnhof",
            "line": {
                "mode": "LongDistanceTrain",
                "name": "ICE 1559",
                "operatorName": "DB Fernverkehr AG"
            }
        },
        "scheduledArrivalTime": "2024-02-11T13:24:00Z",
        "stopPoint": {
            "country": "DE",
            "identifier": {
                "motis": "de:14713:8010205_G"
            },
            "latitude": 51.34547424316406,
            "longitude": 12.382063865661621,
            "name": "Leipzig Hbf",
            "region": "DE-SN",
            "type": "Stop"
        }
    }
]
