{"reisetag":"2025-02-02","regulaereVerkehrstage":"täglich","irregulaereVerkehrstage":"nicht 21. Jan 2025, 6. bis 8. Feb 2025, 18., 22. Feb 2025","zugName":"ICE 19","halte":[{"id":"A=1@O=Bruxelles Midi@X=4335695@Y=50835375@U=81@L=8800004@i=U×008814001@","abfahrtsZeitpunkt":"2025-02-02T18:25:00","auslastungsmeldungen":[{"klasse":"KLASSE_1","stufe":0},{"klasse":"KLASSE_2","stufe":0}],"name":"Bruxelles Midi","risNotizen":[],"extId":"8800004","routeIdx":0,"priorisierteMeldungen":[],"adminID":"80","kategorie":"ICE","nummer":"19"},{"id":"A=1@O=Bruxelles-Nord@X=4361458@Y=50860239@U=81@L=8800002@i=U×008812005@","abfahrtsZeitpunkt":"2025-02-02T18:34:00","ankunftsZeitpunkt":"2025-02-02T18:32:00","auslastungsmeldungen":[{"klasse":"KLASSE_1","stufe":0},{"klasse":"KLASSE_2","stufe":0}],"gleis":"3","platformType":{"code":"PL","shortDescription":"Gl.","longDescription":"Gleis","translations":{"en":{"shortDescription":"Pl.","longDescription":"Track"},"fr":{"shortDescription":""},"it":{"shortDescription":""},"cs":{"shortDescription":""},"da":{"shortDescription":""},"es":{"shortDescription":""},"nl":{"shortDescription":""},"pl":{"shortDescription":""}}},"name":"Bruxelles-Nord","risNotizen":[],"extId":"8800002","routeIdx":1,"priorisierteMeldungen":[],"adminID":"80","kategorie":"ICE","nummer":"19"},{"id":"A=1@O=Liège-Guillemins@X=5566480@Y=50624362@U=81@L=8800012@i=U×008841004@","abfahrtsZeitpunkt":"2025-02-02T19:14:00","ankunftsZeitpunkt":"2025-02-02T19:12:00","auslastungsmeldungen":[{"klasse":"KLASSE_1","stufe":0},{"klasse":"KLASSE_2","stufe":0}],"gleis":"1","platformType":{"code":"PL","shortDescription":"Gl.","longDescription":"Gleis","translations":{"en":{"shortDescription":"Pl.","longDescription":"Track"},"fr":{"shortDescription":""},"it":{"shortDescription":""},"cs":{"shortDescription":""},"da":{"shortDescription":""},"es":{"shortDescription":""},"nl":{"shortDescription":""},"pl":{"shortDescription":""}}},"name":"Liège-Guillemins","risNotizen":[],"extId":"8800012","routeIdx":2,"priorisierteMeldungen":[],"adminID":"80","kategorie":"ICE","nummer":"19"},{"id":"A=1@O=Aachen Hbf@X=6091495@Y=50767803@U=81@L=8000001@i=U×008015345@","abfahrtsZeitpunkt":"2025-02-02T19:39:00","ankunftsZeitpunkt":"2025-02-02T19:36:00","auslastungsmeldungen":[{"klasse":"KLASSE_1","stufe":2},{"klasse":"KLASSE_2","stufe":2}],"gleis":"9","platformType":{"code":"PL","shortDescription":"Gl.","longDescription":"Gleis","translations":{"en":{"shortDescription":"Pl.","longDescription":"Track"},"fr":{"shortDescription":""},"it":{"shortDescription":""},"cs":{"shortDescription":""},"da":{"shortDescription":""},"es":{"shortDescription":""},"nl":{"shortDescription":""},"pl":{"shortDescription":""}}},"name":"Aachen Hbf","risNotizen":[],"bahnhofsInfoId":"0001","extId":"8000001","routeIdx":4,"priorisierteMeldungen":[],"adminID":"80","kategorie":"ICE","nummer":"19"},{"id":"A=1@O=Köln Hbf@X=6958730@Y=50943029@U=81@L=8000207@i=U×008015458@","abfahrtsZeitpunkt":"2025-02-02T20:20:00","ankunftsZeitpunkt":"2025-02-02T20:15:00","auslastungsmeldungen":[{"klasse":"KLASSE_1","stufe":1},{"klasse":"KLASSE_2","stufe":2}],"gleis":"4 A-C","platformType":{"code":"PL","shortDescription":"Gl.","longDescription":"Gleis","translations":{"en":{"shortDescription":"Pl.","longDescription":"Track"},"fr":{"shortDescription":""},"it":{"shortDescription":""},"cs":{"shortDescription":""},"da":{"shortDescription":""},"es":{"shortDescription":""},"nl":{"shortDescription":""},"pl":{"shortDescription":""}}},"name":"Köln Hbf","risNotizen":[],"bahnhofsInfoId":"3320","extId":"8000207","routeIdx":5,"priorisierteMeldungen":[],"adminID":"80","kategorie":"ICE","nummer":"19"},{"id":"A=1@O=Siegburg/Bonn@X=7203029@Y=50793916@U=81@L=8005556@i=U×008015588@","abfahrtsZeitpunkt":"2025-02-02T20:34:00","ankunftsZeitpunkt":"2025-02-02T20:33:00","auslastungsmeldungen":[{"klasse":"KLASSE_1","stufe":1},{"klasse":"KLASSE_2","stufe":2}],"gleis":"6","platformType":{"code":"PL","shortDescription":"Gl.","longDescription":"Gleis","translations":{"en":{"shortDescription":"Pl.","longDescription":"Track"},"fr":{"shortDescription":""},"it":{"shortDescription":""},"cs":{"shortDescription":""},"da":{"shortDescription":""},"es":{"shortDescription":""},"nl":{"shortDescription":""},"pl":{"shortDescription":""}}},"name":"Siegburg/Bonn","risNotizen":[],"bahnhofsInfoId":"5840","extId":"8005556","routeIdx":6,"priorisierteMeldungen":[],"adminID":"80","kategorie":"ICE","nummer":"19"},{"id":"A=1@O=Frankfurt(M) Flughafen Fernbf@X=8570181@Y=50053169@U=81@L=8070003@i=U×008061676@","abfahrtsZeitpunkt":"2025-02-02T21:19:00","ankunftsZeitpunkt":"2025-02-02T21:17:00","auslastungsmeldungen":[{"klasse":"KLASSE_1","stufe":0},{"klasse":"KLASSE_2","stufe":0}],"gleis":"Fern 4","platformType":{"code":"PL","shortDescription":"Gl.","longDescription":"Gleis","translations":{"en":{"shortDescription":"Pl.","longDescription":"Track"},"fr":{"shortDescription":""},"it":{"shortDescription":""},"cs":{"shortDescription":""},"da":{"shortDescription":""},"es":{"shortDescription":""},"nl":{"shortDescription":""},"pl":{"shortDescription":""}}},"name":"Frankfurt(M) Flughafen Fernbf","risNotizen":[],"bahnhofsInfoId":"7982","extId":"8070003","routeIdx":7,"priorisierteMeldungen":[],"adminID":"80","kategorie":"ICE","nummer":"19"},{"id":"A=1@O=Frankfurt(Main)Hbf@X=8663785@Y=50107149@U=81@L=8000105@i=U×008011068@","ankunftsZeitpunkt":"2025-02-02T21:31:00","auslastungsmeldungen":[{"klasse":"KLASSE_1","stufe":0},{"klasse":"KLASSE_2","stufe":0}],"gleis":"19","platformType":{"code":"PL","shortDescription":"Gl.","longDescription":"Gleis","translations":{"en":{"shortDescription":"Pl.","longDescription":"Track"},"fr":{"shortDescription":""},"it":{"shortDescription":""},"cs":{"shortDescription":""},"da":{"shortDescription":""},"es":{"shortDescription":""},"nl":{"shortDescription":""},"pl":{"shortDescription":""}}},"name":"Frankfurt(Main)Hbf","risNotizen":[],"bahnhofsInfoId":"1866","extId":"8000105","routeIdx":8,"priorisierteMeldungen":[],"adminID":"80","kategorie":"ICE","nummer":"19"}],"himMeldungen":[{"ueberschrift":"Information.","text":"Nach dem Halt in Aachen Hbf finden Grenzkontrollen statt. Bitte halten Sie Ihren Reisepass oder Personalausweis bereit.","prioritaet":"HOCH","modDateTime":"2025-01-02T13:59:53"}],"risNotizen":[],"zugattribute":[{"kategorie":"BORDBISTRO","key":"BR","value":"Bordrestaurant"},{"kategorie":"FAHRRADMITNAHME","key":"FR","value":"Fahrradmitnahme reservierungspflichtig"},{"kategorie":"FAHRRADMITNAHME","key":"FB","value":"Fahrradmitnahme begrenzt möglich"},{"kategorie":"INFORMATION","key":"CK","value":"Komfort Check-in verfügbar - wenn möglich bitte einchecken"},{"kategorie":"INFORMATION","key":"FH","value":"Einstieg mit Rollstuhl mit fahrzeuggebundener Einstiegshilfe"}],"priorisierteMeldungen":[{"prioritaet":"HOCH","text":"Nach dem Halt in Aachen Hbf finden Grenzkontrollen statt. Bitte halten Sie Ihren Reisepass oder Personalausweis bereit."}],"abfahrtsZeitpunkt":"2025-02-02T18:25:00","ankunftsZeitpunkt":"2025-02-02T21:31:00","cancelled":false,"polylineGroup":{"polylineDescriptions":[{"coordinates":[{"lng":4.335695,"lat":50.835375},{"lng":4.361458,"lat":50.860239},{"lng":5.56648,"lat":50.624362},{"lng":6.041317,"lat":50.718497},{"lng":6.041317,"lat":50.718497},{"lng":6.041794,"lat":50.720996},{"lng":6.044769,"lat":50.729886},{"lng":6.046037,"lat":50.733203},{"lng":6.047493,"lat":50.736116},{"lng":6.048158,"lat":50.736997},{"lng":6.0493,"lat":50.737985},{"lng":6.050352,"lat":50.738606},{"lng":6.051277,"lat":50.739019},{"lng":6.055556,"lat":50.740502},{"lng":6.064555,"lat":50.744098},{"lng":6.0662,"lat":50.744934},{"lng":6.068105,"lat":50.746273},{"lng":6.071575,"lat":50.749644},{"lng":6.071575,"lat":50.749644},{"lng":6.085751,"lat":50.76365},{"lng":6.087495,"lat":50.765609},{"lng":6.088331,"lat":50.766328},{"lng":6.089338,"lat":50.766958},{"lng":6.089931,"lat":50.767209},{"lng":6.091235,"lat":50.76756},{"lng":6.091235,"lat":50.76756},{"lng":6.092601,"lat":50.767776},{"lng":6.094003,"lat":50.76765},{"lng":6.099145,"lat":50.766373},{"lng":6.101159,"lat":50.76578},{"lng":6.103271,"lat":50.76534},{"lng":6.105384,"lat":50.765241},{"lng":6.106786,"lat":50.765367},{"lng":6.108458,"lat":50.765726},{"lng":6.109986,"lat":50.766292},{"lng":6.114121,"lat":50.768809},{"lng":6.114705,"lat":50.769196},{"lng":6.115541,"lat":50.769753},{"lng":6.116512,"lat":50.770275},{"lng":6.116512,"lat":50.770275},{"lng":6.119371,"lat":50.771758},{"lng":6.123209,"lat":50.774392},{"lng":6.123209,"lat":50.774392},{"lng":6.123209,"lat":50.774392},{"lng":6.125232,"lat":50.775659},{"lng":6.129034,"lat":50.777682},{"lng":6.130185,"lat":50.778203},{"lng":6.144316,"lat":50.783363},{"lng":6.146842,"lat":50.784181},{"lng":6.148801,"lat":50.784702},{"lng":6.154582,"lat":50.785574},{"lng":6.154582,"lat":50.785574},{"lng":6.210297,"lat":50.792847},{"lng":6.213695,"lat":50.793485},{"lng":6.216922,"lat":50.79442},{"lng":6.218288,"lat":50.794914},{"lng":6.218288,"lat":50.794914},{"lng":6.218324,"lat":50.794932},{"lng":6.218324,"lat":50.794932},{"lng":6.219376,"lat":50.795337},{"lng":6.219376,"lat":50.795337},{"lng":6.21978,"lat":50.795112},{"lng":6.220697,"lat":50.795615},{"lng":6.220508,"lat":50.795813},{"lng":6.222837,"lat":50.796883},{"lng":6.229516,"lat":50.800227},{"lng":6.231152,"lat":50.80109},{"lng":6.23259,"lat":50.802079},{"lng":6.233696,"lat":50.803229},{"lng":6.234541,"lat":50.80447},{"lng":6.23579,"lat":50.807508},{"lng":6.236788,"lat":50.809189},{"lng":6.238262,"lat":50.810726},{"lng":6.240159,"lat":50.812057},{"lng":6.242478,"lat":50.81309},{"lng":6.244429,"lat":50.813621},{"lng":6.245804,"lat":50.813845},{"lng":6.248627,"lat":50.813971},{"lng":6.250029,"lat":50.813863},{"lng":6.25198,"lat":50.813558},{"lng":6.25198,"lat":50.813558},{"lng":6.253418,"lat":50.813216},{"lng":6.254676,"lat":50.812803},{"lng":6.255845,"lat":50.812299},{"lng":6.258578,"lat":50.81087},{"lng":6.26042,"lat":50.810187},{"lng":6.263531,"lat":50.809423},{"lng":6.266434,"lat":50.808847},{"lng":6.271927,"lat":50.807939},{"lng":6.278902,"lat":50.80713},{"lng":6.283136,"lat":50.806852},{"lng":6.288934,"lat":50.806897},{"lng":6.288934,"lat":50.806897},{"lng":6.293024,"lat":50.80722},{"lng":6.297177,"lat":50.807814},{"lng":6.301205,"lat":50.808677},{"lng":6.303811,"lat":50.809396},{"lng":6.306328,"lat":50.810223},{"lng":6.308738,"lat":50.811167},{"lng":6.311587,"lat":50.812506},{"lng":6.321727,"lat":50.818133},{"lng":6.323938,"lat":50.819257},{"lng":6.325125,"lat":50.81976},{"lng":6.327004,"lat":50.82039},{"lng":6.329682,"lat":50.820974},{"lng":6.331777,"lat":50.821217},{"lng":6.333188,"lat":50.821279},{"lng":6.33531,"lat":50.821226},{"lng":6.336712,"lat":50.821091},{"lng":6.354151,"lat":50.817774},{"lng":6.354151,"lat":50.817774},{"lng":6.359095,"lat":50.816731},{"lng":6.416653,"lat":50.805342},{"lng":6.416653,"lat":50.805342},{"lng":6.445769,"lat":50.799615},{"lng":6.445769,"lat":50.799615},{"lng":6.445769,"lat":50.799615},{"lng":6.449913,"lat":50.799076},{"lng":6.452736,"lat":50.798914},{"lng":6.454156,"lat":50.798914},{"lng":6.459091,"lat":50.799265},{"lng":6.461168,"lat":50.799553},{"lng":6.463873,"lat":50.800101},{"lng":6.469698,"lat":50.801737},{"lng":6.47217,"lat":50.802627},{"lng":6.473914,"lat":50.803391},{"lng":6.476593,"lat":50.804865},{"lng":6.48009,"lat":50.80758},{"lng":6.48169,"lat":50.808946},{"lng":6.481699,"lat":50.808946},{"lng":6.48169,"lat":50.808946},{"lng":6.482319,"lat":50.809477},{"lng":6.482319,"lat":50.809477},{"lng":6.498086,"lat":50.823284},{"lng":6.498086,"lat":50.823284},{"lng":6.498086,"lat":50.823284},{"lng":6.511076,"lat":50.834673},{"lng":6.511184,"lat":50.834619},{"lng":6.511184,"lat":50.834619},{"lng":6.515283,"lat":50.838134},{"lng":6.517809,"lat":50.839896},{"lng":6.517809,"lat":50.839896},{"lng":6.520901,"lat":50.841541},{"lng":6.524434,"lat":50.843042},{"lng":6.574504,"lat":50.862414},{"lng":6.574504,"lat":50.862414},{"lng":6.576194,"lat":50.863097},{"lng":6.576086,"lat":50.863196},{"lng":6.576086,"lat":50.863196},{"lng":6.604042,"lat":50.873974},{"lng":6.604105,"lat":50.873902},{"lng":6.604042,"lat":50.873974},{"lng":6.626129,"lat":50.882514},{"lng":6.626129,"lat":50.882514},{"lng":6.626129,"lat":50.882514},{"lng":6.669816,"lat":50.899333},{"lng":6.669816,"lat":50.899333},{"lng":6.681125,"lat":50.903782},{"lng":6.681188,"lat":50.90372},{"lng":6.681125,"lat":50.903782},{"lng":6.706178,"lat":50.913455},{"lng":6.713513,"lat":50.916403},{"lng":6.713513,"lat":50.916403},{"lng":6.725343,"lat":50.920718},{"lng":6.734296,"lat":50.923999},{"lng":6.762001,"lat":50.933186},{"lng":6.764607,"lat":50.933905},{"lng":6.767286,"lat":50.934517},{"lng":6.778217,"lat":50.936638},{"lng":6.778262,"lat":50.936539},{"lng":6.782316,"lat":50.937267},{"lng":6.785094,"lat":50.937654},{"lng":6.796294,"lat":50.938921},{"lng":6.814947,"lat":50.940872},{"lng":6.814947,"lat":50.940872},{"lng":6.834606,"lat":50.942921},{"lng":6.83458,"lat":50.94302},{"lng":6.835263,"lat":50.943101},{"lng":6.835263,"lat":50.943101},{"lng":6.835263,"lat":50.943101},{"lng":6.878249,"lat":50.947524},{"lng":6.882043,"lat":50.947919},{"lng":6.885521,"lat":50.948315},{"lng":6.885521,"lat":50.948297},{"lng":6.885548,"lat":50.948216},{"lng":6.888137,"lat":50.948531},{"lng":6.888137,"lat":50.948531},{"lng":6.892659,"lat":50.949025},{"lng":6.892533,"lat":50.949529},{"lng":6.892641,"lat":50.949115},{"lng":6.909379,"lat":50.950715},{"lng":6.917199,"lat":50.951758},{"lng":6.917226,"lat":50.951677},{"lng":6.922593,"lat":50.952046},{"lng":6.925613,"lat":50.952414},{"lng":6.925595,"lat":50.952468},{"lng":6.925613,"lat":50.952414},{"lng":6.933101,"lat":50.953223},{"lng":6.937164,"lat":50.95405},{"lng":6.938576,"lat":50.954149},{"lng":6.939286,"lat":50.954113},{"lng":6.940634,"lat":50.953852},{"lng":6.941785,"lat":50.953322},{"lng":6.943421,"lat":50.951857},{"lng":6.944437,"lat":50.951228},{"lng":6.945695,"lat":50.950823},{"lng":6.948527,"lat":50.950374},{"lng":6.950549,"lat":50.94987},{"lng":6.950657,"lat":50.949978},{"lng":6.950657,"lat":50.949978},{"lng":6.951277,"lat":50.949699},{"lng":6.952374,"lat":50.94898},{"lng":6.952437,"lat":50.949016},{"lng":6.959125,"lat":50.942796},{"lng":6.9597,"lat":50.943038},{"lng":6.9597,"lat":50.943038},{"lng":6.960033,"lat":50.942724},{"lng":6.960491,"lat":50.942301},{"lng":6.961282,"lat":50.941825},{"lng":6.962253,"lat":50.941582},{"lng":6.971467,"lat":50.941492},{"lng":6.974658,"lat":50.941285},{"lng":6.974551,"lat":50.940971},{"lng":6.975162,"lat":50.940602},{"lng":6.97527,"lat":50.940989},{"lng":6.977984,"lat":50.940692},{"lng":6.979477,"lat":50.940458},{"lng":6.98256,"lat":50.940198},{"lng":6.982578,"lat":50.940288},{"lng":6.98256,"lat":50.940198},{"lng":6.984412,"lat":50.940054},{"lng":6.986551,"lat":50.940045},{"lng":6.987962,"lat":50.940234},{"lng":6.987962,"lat":50.940234},{"lng":6.987657,"lat":50.939497},{"lng":6.988942,"lat":50.9392},{"lng":6.993536,"lat":50.937294},{"lng":6.993437,"lat":50.937204},{"lng":6.993437,"lat":50.937204},{"lng":6.994498,"lat":50.936755},{"lng":6.995666,"lat":50.936251},{"lng":6.996664,"lat":50.93582},{"lng":6.996754,"lat":50.93591},{"lng":7.000664,"lat":50.934301},{"lng":7.005743,"lat":50.932036},{"lng":7.005689,"lat":50.931991},{"lng":7.005743,"lat":50.932036},{"lng":7.015362,"lat":50.928008},{"lng":7.017546,"lat":50.926867},{"lng":7.021339,"lat":50.924664},{"lng":7.021339,"lat":50.924664},{"lng":7.02125,"lat":50.92461},{"lng":7.026167,"lat":50.921689},{"lng":7.026679,"lat":50.921374},{"lng":7.026688,"lat":50.921383},{"lng":7.032944,"lat":50.917509},{"lng":7.033052,"lat":50.917581},{"lng":7.032998,"lat":50.917545},{"lng":7.044541,"lat":50.910309},{"lng":7.044541,"lat":50.910309},{"lng":7.048622,"lat":50.907144},{"lng":7.050995,"lat":50.904906},{"lng":7.052523,"lat":50.903171},{"lng":7.052388,"lat":50.903126},{"lng":7.052523,"lat":50.903171},{"lng":7.053341,"lat":50.902137},{"lng":7.055256,"lat":50.899225},{"lng":7.050968,"lat":50.901239},{"lng":7.055283,"lat":50.898847},{"lng":7.057197,"lat":50.895593},{"lng":7.057368,"lat":50.895081},{"lng":7.057368,"lat":50.895081},{"lng":7.057548,"lat":50.894245},{"lng":7.057566,"lat":50.894245},{"lng":7.059112,"lat":50.891899},{"lng":7.060362,"lat":50.889741},{"lng":7.060317,"lat":50.889732},{"lng":7.060469,"lat":50.889759},{"lng":7.065162,"lat":50.881894},{"lng":7.065261,"lat":50.881921},{"lng":7.065162,"lat":50.881894},{"lng":7.066187,"lat":50.880141},{"lng":7.066294,"lat":50.880168},{"lng":7.079257,"lat":50.858126},{"lng":7.079257,"lat":50.858126},{"lng":7.080165,"lat":50.856571},{"lng":7.081639,"lat":50.854333},{"lng":7.083491,"lat":50.852319},{"lng":7.087518,"lat":50.848957},{"lng":7.087347,"lat":50.848885},{"lng":7.087347,"lat":50.848876},{"lng":7.112742,"lat":50.828174},{"lng":7.114477,"lat":50.826871},{"lng":7.114351,"lat":50.826808},{"lng":7.116499,"lat":50.825459},{"lng":7.119708,"lat":50.823859},{"lng":7.127574,"lat":50.820785},{"lng":7.127628,"lat":50.820857},{"lng":7.12752,"lat":50.820354},{"lng":7.128796,"lat":50.820039},{"lng":7.128796,"lat":50.820039},{"lng":7.12921,"lat":50.82056},{"lng":7.132042,"lat":50.819679},{"lng":7.134334,"lat":50.819185},{"lng":7.135296,"lat":50.818879},{"lng":7.135296,"lat":50.818879},{"lng":7.135871,"lat":50.8187},{"lng":7.139503,"lat":50.817315},{"lng":7.150685,"lat":50.813684},{"lng":7.150811,"lat":50.813836},{"lng":7.187002,"lat":50.802348},{"lng":7.191379,"lat":50.800856},{"lng":7.193681,"lat":50.799813},{"lng":7.195784,"lat":50.798609},{"lng":7.202499,"lat":50.793979},{"lng":7.202499,"lat":50.793979},{"lng":7.203164,"lat":50.793521},{"lng":7.203164,"lat":50.793521},{"lng":7.211569,"lat":50.78766},{"lng":7.213367,"lat":50.786275},{"lng":7.215731,"lat":50.784028},{"lng":7.21734,"lat":50.782033},{"lng":7.218383,"lat":50.780361},{"lng":7.21921,"lat":50.778644},{"lng":7.219794,"lat":50.776882},{"lng":7.221322,"lat":50.77112},{"lng":7.222293,"lat":50.768495},{"lng":7.223875,"lat":50.765043},{"lng":7.22579,"lat":50.761663},{"lng":7.233835,"lat":50.749177},{"lng":7.235768,"lat":50.745806},{"lng":7.237134,"lat":50.742318},{"lng":7.237872,"lat":50.73875},{"lng":7.237997,"lat":50.736961},{"lng":7.237791,"lat":50.726174},{"lng":7.237961,"lat":50.723477},{"lng":7.238285,"lat":50.721688},{"lng":7.238761,"lat":50.719917},{"lng":7.239409,"lat":50.718173},{"lng":7.240676,"lat":50.715602},{"lng":7.242303,"lat":50.713112},{"lng":7.244272,"lat":50.710721},{"lng":7.246564,"lat":50.708447},{"lng":7.249162,"lat":50.706316},{"lng":7.252048,"lat":50.704339},{"lng":7.259149,"lat":50.699952},{"lng":7.262772,"lat":50.697192},{"lng":7.265163,"lat":50.694963},{"lng":7.277181,"lat":50.682783},{"lng":7.279698,"lat":50.680607},{"lng":7.281532,"lat":50.679241},{"lng":7.283483,"lat":50.677937},{"lng":7.28555,"lat":50.676715},{"lng":7.29,"lat":50.674495},{"lng":7.293578,"lat":50.673047},{"lng":7.305902,"lat":50.668634},{"lng":7.309381,"lat":50.667096},{"lng":7.313678,"lat":50.664759},{"lng":7.317525,"lat":50.662125},{"lng":7.320087,"lat":50.659977},{"lng":7.322361,"lat":50.657703},{"lng":7.327233,"lat":50.652228},{"lng":7.330451,"lat":50.649271},{"lng":7.332249,"lat":50.647887},{"lng":7.33518,"lat":50.645936},{"lng":7.337274,"lat":50.644722},{"lng":7.340654,"lat":50.64296},{"lng":7.340654,"lat":50.64296},{"lng":7.34505,"lat":50.640839},{"lng":7.349769,"lat":50.638861},{"lng":7.386301,"lat":50.625171},{"lng":7.392585,"lat":50.623121},{"lng":7.406725,"lat":50.619013},{"lng":7.411804,"lat":50.617449},{"lng":7.415471,"lat":50.616092},{"lng":7.418932,"lat":50.614537},{"lng":7.421126,"lat":50.613404},{"lng":7.423202,"lat":50.61219},{"lng":7.427032,"lat":50.609548},{"lng":7.429576,"lat":50.60739},{"lng":7.435454,"lat":50.601781},{"lng":7.437621,"lat":50.60001},{"lng":7.439491,"lat":50.598662},{"lng":7.459698,"lat":50.586104},{"lng":7.463923,"lat":50.583722},{"lng":7.467339,"lat":50.58213},{"lng":7.472202,"lat":50.580306},{"lng":7.477362,"lat":50.578849},{"lng":7.498828,"lat":50.574382},{"lng":7.504132,"lat":50.57315},{"lng":7.509193,"lat":50.571568},{"lng":7.513265,"lat":50.56995},{"lng":7.513256,"lat":50.56995},{"lng":7.513265,"lat":50.56995},{"lng":7.521283,"lat":50.566175},{"lng":7.521283,"lat":50.566175},{"lng":7.526443,"lat":50.563765},{"lng":7.528816,"lat":50.562795},{"lng":7.532538,"lat":50.5615},{"lng":7.536412,"lat":50.56043},{"lng":7.539073,"lat":50.559828},{"lng":7.543163,"lat":50.559127},{"lng":7.545932,"lat":50.558785},{"lng":7.555703,"lat":50.557869},{"lng":7.558454,"lat":50.557473},{"lng":7.56116,"lat":50.55697},{"lng":7.565124,"lat":50.556035},{"lng":7.567695,"lat":50.55528},{"lng":7.570185,"lat":50.554444},{"lng":7.573771,"lat":50.553014},{"lng":7.577142,"lat":50.551387},{"lng":7.579264,"lat":50.550201},{"lng":7.581277,"lat":50.548933},{"lng":7.584055,"lat":50.546902},{"lng":7.587327,"lat":50.54398},{"lng":7.593961,"lat":50.537077},{"lng":7.595534,"lat":50.535584},{"lng":7.597233,"lat":50.534155},{"lng":7.600011,"lat":50.532123},{"lng":7.603058,"lat":50.530254},{"lng":7.60749,"lat":50.528024},{"lng":7.612281,"lat":50.526137},{"lng":7.616084,"lat":50.524959},{"lng":7.62003,"lat":50.523988},{"lng":7.624093,"lat":50.523242},{"lng":7.628237,"lat":50.522712},{"lng":7.632444,"lat":50.522415},{"lng":7.63808,"lat":50.522352},{"lng":7.663457,"lat":50.522721},{"lng":7.667682,"lat":50.522658},{"lng":7.671889,"lat":50.522379},{"lng":7.677417,"lat":50.521669},{"lng":7.682793,"lat":50.52059},{"lng":7.686685,"lat":50.519539},{"lng":7.691647,"lat":50.517831},{"lng":7.695153,"lat":50.516329},{"lng":7.698479,"lat":50.514666},{"lng":7.719918,"lat":50.502989},{"lng":7.724997,"lat":50.499879},{"lng":7.731622,"lat":50.495214},{"lng":7.734615,"lat":50.493308},{"lng":7.737771,"lat":50.491519},{"lng":7.74542,"lat":50.487546},{"lng":7.74747,"lat":50.486314},{"lng":7.750329,"lat":50.484328},{"lng":7.752082,"lat":50.482917},{"lng":7.754464,"lat":50.480696},{"lng":7.75654,"lat":50.47835},{"lng":7.757754,"lat":50.476723},{"lng":7.759722,"lat":50.473352},{"lng":7.762788,"lat":50.466439},{"lng":7.764325,"lat":50.463922},{"lng":7.766186,"lat":50.461504},{"lng":7.769152,"lat":50.458448},{"lng":7.771714,"lat":50.456308},{"lng":7.774555,"lat":50.454313},{"lng":7.777647,"lat":50.452479},{"lng":7.782123,"lat":50.450304},{"lng":7.78696,"lat":50.448461},{"lng":7.792092,"lat":50.446978},{"lng":7.797441,"lat":50.445881},{"lng":7.80296,"lat":50.445162},{"lng":7.807158,"lat":50.444892},{"lng":7.825173,"lat":50.44473},{"lng":7.825173,"lat":50.44491},{"lng":7.825254,"lat":50.44473},{"lng":7.825254,"lat":50.44473},{"lng":7.842351,"lat":50.444569},{"lng":7.845156,"lat":50.444443},{"lng":7.849345,"lat":50.444092},{"lng":7.853471,"lat":50.443535},{"lng":7.857534,"lat":50.442798},{"lng":7.861498,"lat":50.441863},{"lng":7.865346,"lat":50.440757},{"lng":7.867836,"lat":50.439912},{"lng":7.87144,"lat":50.43851},{"lng":7.87375,"lat":50.437485},{"lng":7.877059,"lat":50.435813},{"lng":7.881167,"lat":50.433359},{"lng":7.89394,"lat":50.42499},{"lng":7.896008,"lat":50.423776},{"lng":7.89928,"lat":50.422069},{"lng":7.902732,"lat":50.420522},{"lng":7.906363,"lat":50.419138},{"lng":7.91013,"lat":50.417924},{"lng":7.915353,"lat":50.416594},{"lng":7.919389,"lat":50.415812},{"lng":7.92213,"lat":50.41539},{"lng":7.926985,"lat":50.414868},{"lng":7.931884,"lat":50.414589},{"lng":7.964191,"lat":50.413412},{"lng":7.96838,"lat":50.413133},{"lng":7.971158,"lat":50.412828},{"lng":7.975257,"lat":50.412198},{"lng":7.980578,"lat":50.41103},{"lng":7.983158,"lat":50.410311},{"lng":7.994494,"lat":50.406706},{"lng":7.998386,"lat":50.405672},{"lng":8.003752,"lat":50.404602},{"lng":8.008148,"lat":50.404027},{"lng":8.008148,"lat":50.404027},{"lng":8.012068,"lat":50.403713},{"lng":8.014881,"lat":50.403605},{"lng":8.048636,"lat":50.403452},{"lng":8.052141,"lat":50.403344},{"lng":8.055638,"lat":50.403083},{"lng":8.058398,"lat":50.402751},{"lng":8.061131,"lat":50.402319},{"lng":8.06514,"lat":50.401474},{"lng":8.070264,"lat":50.4},{"lng":8.073904,"lat":50.398643},{"lng":8.077347,"lat":50.397079},{"lng":8.079514,"lat":50.395937},{"lng":8.081572,"lat":50.394705},{"lng":8.083505,"lat":50.393402},{"lng":8.085752,"lat":50.391676},{"lng":8.096225,"lat":50.38239},{"lng":8.095487,"lat":50.382049},{"lng":8.096225,"lat":50.38239},{"lng":8.096135,"lat":50.382462},{"lng":8.096135,"lat":50.382462},{"lng":8.102616,"lat":50.376727},{"lng":8.105313,"lat":50.374659},{"lng":8.107245,"lat":50.373356},{"lng":8.110356,"lat":50.371531},{"lng":8.112549,"lat":50.370408},{"lng":8.114832,"lat":50.369365},{"lng":8.120774,"lat":50.366974},{"lng":8.120774,"lat":50.366974},{"lng":8.129161,"lat":50.363666},{"lng":8.134051,"lat":50.361895},{"lng":8.139166,"lat":50.360412},{"lng":8.152272,"lat":50.357175},{"lng":8.154861,"lat":50.356465},{"lng":8.158619,"lat":50.355252},{"lng":8.163374,"lat":50.353337},{"lng":8.165621,"lat":50.352258},{"lng":8.168812,"lat":50.350496},{"lng":8.183959,"lat":50.341121},{"lng":8.187168,"lat":50.339377},{"lng":8.190566,"lat":50.337786},{"lng":8.208356,"lat":50.330558},{"lng":8.211772,"lat":50.328985},{"lng":8.213929,"lat":50.327835},{"lng":8.216986,"lat":50.325974},{"lng":8.220662,"lat":50.323259},{"lng":8.223871,"lat":50.320311},{"lng":8.225939,"lat":50.317964},{"lng":8.23393,"lat":50.307456},{"lng":8.236223,"lat":50.304175},{"lng":8.237463,"lat":50.302072},{"lng":8.238533,"lat":50.299932},{"lng":8.240034,"lat":50.296004},{"lng":8.240816,"lat":50.292894},{"lng":8.241221,"lat":50.290215},{"lng":8.242389,"lat":50.277648},{"lng":8.242982,"lat":50.274978},{"lng":8.245742,"lat":50.266169},{"lng":8.246443,"lat":50.2626},{"lng":8.246614,"lat":50.259912},{"lng":8.246551,"lat":50.258114},{"lng":8.245571,"lat":50.25095},{"lng":8.245436,"lat":50.249152},{"lng":8.245436,"lat":50.247354},{"lng":8.245697,"lat":50.244666},{"lng":8.246524,"lat":50.241107},{"lng":8.251163,"lat":50.227039},{"lng":8.252088,"lat":50.223488},{"lng":8.25252,"lat":50.21991},{"lng":8.252331,"lat":50.210921},{"lng":8.25279,"lat":50.207334},{"lng":8.253841,"lat":50.20381},{"lng":8.255019,"lat":50.201213},{"lng":8.255981,"lat":50.199532},{"lng":8.258012,"lat":50.196664},{"lng":8.262849,"lat":50.191127},{"lng":8.262849,"lat":50.191127},{"lng":8.274247,"lat":50.17829},{"lng":8.276548,"lat":50.176034},{"lng":8.27822,"lat":50.174595},{"lng":8.280926,"lat":50.172537},{"lng":8.282868,"lat":50.171234},{"lng":8.295255,"lat":50.163952},{"lng":8.298275,"lat":50.162083},{"lng":8.300172,"lat":50.160761},{"lng":8.30366,"lat":50.157947},{"lng":8.310015,"lat":50.152024},{"lng":8.312595,"lat":50.149902},{"lng":8.316379,"lat":50.14725},{"lng":8.323256,"lat":50.142774},{"lng":8.327814,"lat":50.139367},{"lng":8.331149,"lat":50.136481},{"lng":8.334906,"lat":50.132688},{"lng":8.336929,"lat":50.130324},{"lng":8.348345,"lat":50.115905},{"lng":8.350098,"lat":50.11346},{"lng":8.352076,"lat":50.110089},{"lng":8.35328,"lat":50.107509},{"lng":8.354503,"lat":50.104003},{"lng":8.355141,"lat":50.101333},{"lng":8.356498,"lat":50.094196},{"lng":8.357235,"lat":50.091544},{"lng":8.358647,"lat":50.088065},{"lng":8.360013,"lat":50.085512},{"lng":8.362242,"lat":50.082222},{"lng":8.364903,"lat":50.079058},{"lng":8.3684,"lat":50.075696},{"lng":8.372247,"lat":50.072613},{"lng":8.372247,"lat":50.072613},{"lng":8.372247,"lat":50.072613},{"lng":8.372247,"lat":50.072613},{"lng":8.375888,"lat":50.069772},{"lng":8.378423,"lat":50.067624},{"lng":8.385587,"lat":50.060972},{"lng":8.388176,"lat":50.058859},{"lng":8.390918,"lat":50.056819},{"lng":8.394801,"lat":50.05423},{"lng":8.405993,"lat":50.047461},{"lng":8.409094,"lat":50.045645},{"lng":8.413481,"lat":50.043425},{"lng":8.418191,"lat":50.041492},{"lng":8.423171,"lat":50.039874},{"lng":8.44773,"lat":50.033429},{"lng":8.455577,"lat":50.031541},{"lng":8.471668,"lat":50.028305},{"lng":8.471668,"lat":50.028305},{"lng":8.471668,"lat":50.028305},{"lng":8.471668,"lat":50.028305},{"lng":8.476909,"lat":50.027289},{"lng":8.479632,"lat":50.026903},{"lng":8.48241,"lat":50.026714},{"lng":8.485197,"lat":50.026723},{"lng":8.488658,"lat":50.02702},{"lng":8.491354,"lat":50.027478},{"lng":8.493952,"lat":50.028125},{"lng":8.497674,"lat":50.029276},{"lng":8.497674,"lat":50.029276},{"lng":8.497674,"lat":50.029276},{"lng":8.497674,"lat":50.029276},{"lng":8.503364,"lat":50.031074},{"lng":8.508263,"lat":50.0328},{"lng":8.534359,"lat":50.043227},{"lng":8.541316,"lat":50.04623},{"lng":8.543726,"lat":50.047137},{"lng":8.546234,"lat":50.047928},{"lng":8.548822,"lat":50.048603},{"lng":8.562468,"lat":50.051479},{"lng":8.569767,"lat":50.052917},{"lng":8.569839,"lat":50.052765},{"lng":8.57419,"lat":50.053574},{"lng":8.576905,"lat":50.053987},{"lng":8.579655,"lat":50.054275},{"lng":8.582433,"lat":50.05441},{"lng":8.585921,"lat":50.054383},{"lng":8.597023,"lat":50.053583},{"lng":8.601832,"lat":50.05343},{"lng":8.601832,"lat":50.053457},{"lng":8.601832,"lat":50.053475},{"lng":8.607495,"lat":50.053349},{"lng":8.609581,"lat":50.053412},{"lng":8.612304,"lat":50.053789},{"lng":8.614848,"lat":50.0545},{"lng":8.617131,"lat":50.055533},{"lng":8.618543,"lat":50.056522},{"lng":8.619612,"lat":50.057682},{"lng":8.622282,"lat":50.06134},{"lng":8.622354,"lat":50.061313},{"lng":8.622327,"lat":50.061322},{"lng":8.622723,"lat":50.061853},{"lng":8.623586,"lat":50.063102},{"lng":8.62426,"lat":50.064073},{"lng":8.62497,"lat":50.064846},{"lng":8.626399,"lat":50.065826},{"lng":8.628161,"lat":50.066545},{"lng":8.633402,"lat":50.068091},{"lng":8.63315,"lat":50.06846},{"lng":8.638283,"lat":50.069889},{"lng":8.639479,"lat":50.070348},{"lng":8.640917,"lat":50.071327},{"lng":8.641771,"lat":50.07255},{"lng":8.641951,"lat":50.073889},{"lng":8.641438,"lat":50.075184},{"lng":8.63929,"lat":50.078015},{"lng":8.636944,"lat":50.080712},{"lng":8.636944,"lat":50.080712},{"lng":8.637294,"lat":50.080829},{"lng":8.637294,"lat":50.080829},{"lng":8.637501,"lat":50.080892},{"lng":8.632755,"lat":50.086798},{"lng":8.631847,"lat":50.088083},{"lng":8.630813,"lat":50.090142},{"lng":8.630525,"lat":50.09069},{"lng":8.630444,"lat":50.090834},{"lng":8.630462,"lat":50.090834},{"lng":8.630184,"lat":50.091274},{"lng":8.629635,"lat":50.092623},{"lng":8.629734,"lat":50.093782},{"lng":8.630211,"lat":50.094618},{"lng":8.63057,"lat":50.095005},{"lng":8.632036,"lat":50.095967},{"lng":8.633806,"lat":50.096704},{"lng":8.63377,"lat":50.09674},{"lng":8.634247,"lat":50.097198},{"lng":8.635784,"lat":50.09674},{"lng":8.636467,"lat":50.096641},{"lng":8.637753,"lat":50.096614},{"lng":8.637753,"lat":50.096614},{"lng":8.637753,"lat":50.096614},{"lng":8.638454,"lat":50.096677},{"lng":8.638175,"lat":50.097702},{"lng":8.638175,"lat":50.097702},{"lng":8.648477,"lat":50.101846},{"lng":8.648486,"lat":50.101846},{"lng":8.648477,"lat":50.101846},{"lng":8.662572,"lat":50.107266}],"delta":false}]}}
